<Properties StartupConfiguration="{564FA317-2006-4987-943D-F6B5A711C67D}|Default">
  <MonoDevelop.Ide.Workbench ActiveDocument="Web/WebScraper.cs">
    <Files>
      <File FileName="Web/Program.cs" Line="12" Column="43" />
      <File FileName="Web/smsSender.cs" Line="26" Column="45" />
      <File FileName="Web/Meals.txt" />
      <File FileName="Web/WebScraper.cs" Line="50" Column="29" />
    </Files>
    <Pads>
      <Pad Id="ProjectPad">
        <State name="__root__">
          <Node name="WebScraper" expanded="True">
            <Node name="WebScraper" expanded="True">
              <Node name="Dependencies" expanded="True" />
              <Node name="WebScraper.cs" selected="True" />
            </Node>
          </Node>
        </State>
      </Pad>
    </Pads>
  </MonoDevelop.Ide.Workbench>
  <MonoDevelop.Ide.ItemProperties.WebScraper PreferredExecutionTarget="MonoDevelop.Default" />
  <MonoDevelop.Ide.DebuggingService.PinnedWatches />
  <MonoDevelop.Ide.Workspace ActiveConfiguration="Debug" />
  <MonoDevelop.Ide.DebuggingService.Breakpoints>
    <BreakpointStore />
  </MonoDevelop.Ide.DebuggingService.Breakpoints>
  <MultiItemStartupConfigurations />
</Properties>